retryrequests/__init__.py
retryrequests/__version__.py
retryrequests/py.typed
retryrequests-0.2.0.dist-info/LICENSE
retryrequests-0.2.0.dist-info/METADATA
retryrequests-0.2.0.dist-info/WHEEL
retryrequests-0.2.0.dist-info/top_level.txt
retryrequests-0.2.0.dist-info/RECORD
